[
  {
    "name": "CFA MIDISUP",
    "city": "Toulouse",
    "sector": "Centre de formation d'apprentis",
    "url": "https://diplomeo.com/etablissement-cfa_midisup-548",
    "description": "",
    "address": "",
    "formations": [],
    "email": "Non trouvé",
    "email_found": false,
    "phone": "Non trouvé",
    "phone_found": false,
    "website": "Non trouvé",
    "website_found": false,
    "processed_at": "2025-03-19T05:28:53.220Z"
  },
  {
    "name": "CFA municipal de Salon-de-Provence",
    "city": "Aix-en-Provence",
    "sector": "Centre de formation d'apprentis",
    "url": "https://diplomeo.com/etablissement-cfa_municipal_de_salon_de_provence-549",
    "description": "",
    "address": "",
    "formations": [],
    "email": "Non trouvé",
    "email_found": false,
    "phone": "Non trouvé",
    "phone_found": false,
    "website": "Non trouvé",
    "website_found": false,
    "processed_at": "2025-03-19T05:28:58.959Z"
  },
  {
    "name": "CFA leem apprentissage",
    "city": "Nanterre",
    "sector": "Centre de formation d'apprentis",
    "url": "https://diplomeo.com/etablissement-cfa_leem_apprentissage-550",
    "description": "",
    "address": "",
    "formations": [],
    "email": "Non trouvé",
    "email_found": false,
    "phone": "Non trouvé",
    "phone_found": false,
    "website": "Non trouvé",
    "website_found": false,
    "processed_at": "2025-03-19T05:29:05.338Z"
  },
  {
    "name": "CFA La Châtaigneraie",
    "city": "Rouen",
    "sector": "Centre de formation d'apprentis",
    "url": "https://diplomeo.com/etablissement-cfa_la_chataigneraie-551",
    "description": "",
    "address": "",
    "formations": [],
    "email": "Non trouvé",
    "email_found": false,
    "phone": "Non trouvé",
    "phone_found": false,
    "website": "Non trouvé",
    "website_found": false,
    "processed_at": "2025-03-19T05:29:10.471Z"
  },
  {
    "name": "CFA Jeanne d'Arc",
    "city": "Rouen",
    "sector": "Centre de formation d'apprentis",
    "url": "https://diplomeo.com/etablissement-cfa_jeanne_d_arc-552",
    "description": "",
    "address": "",
    "formations": [],
    "email": "Non trouvé",
    "email_found": false,
    "phone": "Non trouvé",
    "phone_found": false,
    "website": "Non trouvé",
    "website_found": false,
    "processed_at": "2025-03-19T05:29:16.896Z"
  },
  {
    "name": "CFA Jules Rieffel - site de Guérande",
    "city": "Nantes",
    "sector": "Centre de formation d'apprentis",
    "url": "https://diplomeo.com/etablissement-cfa_jules_rieffel_site_de_guerande-553",
    "description": "",
    "address": "",
    "formations": [],
    "email": "Non trouvé",
    "email_found": false,
    "phone": "Non trouvé",
    "phone_found": false,
    "website": "Non trouvé",
    "website_found": false,
    "processed_at": "2025-03-19T05:29:23.039Z"
  },
  {
    "name": "CFAI 8002 - CFAI 8002 - site de Saint-Quentin",
    "city": "Laon",
    "sector": "Centre de formation d'apprentis",
    "url": "https://diplomeo.com/etablissement-cfai_8002_cfai_8002_site_de_saint_quentin-555",
    "description": "",
    "address": "",
    "formations": [],
    "email": "Non trouvé",
    "email_found": false,
    "phone": "Non trouvé",
    "phone_found": false,
    "website": "Non trouvé",
    "website_found": false,
    "processed_at": "2025-03-19T05:29:29.195Z"
  },
  {
    "name": "CFAI 8002 - CFAI 8002 - site de Chauny",
    "city": "Laon",
    "sector": "Centre de formation d'apprentis",
    "url": "https://diplomeo.com/etablissement-cfai_8002_cfai_8002_site_de_chauny-556",
    "description": "",
    "address": "",
    "formations": [],
    "email": "Non trouvé",
    "email_found": false,
    "phone": "Non trouvé",
    "phone_found": false,
    "website": "Non trouvé",
    "website_found": false,
    "processed_at": "2025-03-19T05:29:34.960Z"
  },
  {
    "name": "CFA le Moulin Rabaud",
    "city": "Limoges",
    "sector": "Centre de formation d'apprentis",
    "url": "https://diplomeo.com/etablissement-cfa_le_moulin_rabaud-558",
    "description": "",
    "address": "",
    "formations": [],
    "email": "Non trouvé",
    "email_found": false,
    "phone": "Non trouvé",
    "phone_found": false,
    "website": "Non trouvé",
    "website_found": false,
    "processed_at": "2025-03-19T05:29:41.481Z"
  },
  {
    "name": "Centre de Formation Alternance/Apprentissage - la Joliverie",
    "city": "Saint-Sébastien-sur-Loire",
    "sector": "Centre de formation d'apprentis",
    "url": "https://diplomeo.com/etablissement-centre_de_formation_alternance_apprentissage_la_joliverie-559",
    "description": "",
    "address": "",
    "formations": [],
    "email": "Non trouvé",
    "email_found": false,
    "phone": "Non trouvé",
    "phone_found": false,
    "website": "Non trouvé",
    "website_found": false,
    "processed_at": "2025-03-19T05:29:47.443Z"
  },
  {
    "name": "CFAI région Nord-Pas de Calais",
    "city": "Arras",
    "sector": "Centre de formation d'apprentis",
    "url": "https://diplomeo.com/etablissement-cfai_region_nord_pas_de_calais-560",
    "description": "",
    "address": "",
    "formations": [],
    "email": "Non trouvé",
    "email_found": false,
    "phone": "Non trouvé",
    "phone_found": false,
    "website": "Non trouvé",
    "website_found": false,
    "processed_at": "2025-03-19T05:29:53.454Z"
  },
  {
    "name": "CFAI 8002 - site de Soissons",
    "city": "Laon",
    "sector": "Centre de formation d'apprentis",
    "url": "https://diplomeo.com/etablissement-cfai_8002_site_de_soissons-561",
    "description": "",
    "address": "",
    "formations": [],
    "email": "Non trouvé",
    "email_found": false,
    "phone": "Non trouvé",
    "phone_found": false,
    "website": "Non trouvé",
    "website_found": false,
    "processed_at": "2025-03-19T05:29:58.990Z"
  },
  {
    "name": "CFAI 21-71 Saône et Loire",
    "city": "Mâcon",
    "sector": "Centre de formation d'apprentis",
    "url": "https://diplomeo.com/etablissement-cfai_21_71_saone_et_loire-562",
    "description": "",
    "address": "",
    "formations": [],
    "email": "Non trouvé",
    "email_found": false,
    "phone": "Non trouvé",
    "phone_found": false,
    "website": "Non trouvé",
    "website_found": false,
    "processed_at": "2025-03-19T05:30:04.652Z"
  },
  {
    "name": "CFAI région Nord-Pas de Calais",
    "city": "Lille",
    "sector": "Centre de formation d'apprentis",
    "url": "https://diplomeo.com/etablissement-cfai_region_nord_pas_de_calais-563",
    "description": "",
    "address": "",
    "formations": [],
    "email": "Non trouvé",
    "email_found": false,
    "phone": "Non trouvé",
    "phone_found": false,
    "website": "Non trouvé",
    "website_found": false,
    "processed_at": "2025-03-19T05:30:10.998Z"
  },
  {
    "name": "Isifa Plus Values",
    "city": "",
    "sector": "École spécialisée",
    "url": "https://diplomeo.com/etablissement-isifa_plus_values-564",
    "description": "",
    "address": "",
    "formations": [],
    "email": "Non trouvé",
    "email_found": false,
    "phone": "Non trouvé",
    "phone_found": false,
    "website": "Non trouvé",
    "website_found": false,
    "processed_at": "2025-03-19T05:30:16.810Z"
  },
  {
    "name": "CFAI région Nord-Pas de Calais",
    "city": "Lille",
    "sector": "Centre de formation d'apprentis",
    "url": "https://diplomeo.com/etablissement-cfai_region_nord_pas_de_calais-565",
    "description": "",
    "address": "",
    "formations": [],
    "email": "Non trouvé",
    "email_found": false,
    "phone": "Non trouvé",
    "phone_found": false,
    "website": "Non trouvé",
    "website_found": false,
    "processed_at": "2025-03-19T05:30:23.259Z"
  },
  {
    "name": "CFAI région havraise",
    "city": "Rouen",
    "sector": "Centre de formation d'apprentis",
    "url": "https://diplomeo.com/etablissement-cfai_region_havraise-566",
    "description": "",
    "address": "",
    "formations": [],
    "email": "Non trouvé",
    "email_found": false,
    "phone": "Non trouvé",
    "phone_found": false,
    "website": "Non trouvé",
    "website_found": false,
    "processed_at": "2025-03-19T05:30:28.982Z"
  },
  {
    "name": "ISD-FLAUBERT - CFA ISD-Flaubert",
    "city": "Rouen",
    "sector": "Centre de formation d'apprentis",
    "url": "https://diplomeo.com/etablissement-isd_flaubert_cfa_isd_flaubert-567",
    "description": "",
    "address": "",
    "formations": [],
    "email": "Non trouvé",
    "email_found": false,
    "phone": "Non trouvé",
    "phone_found": false,
    "website": "Non trouvé",
    "website_found": false,
    "processed_at": "2025-03-19T05:30:35.231Z"
  },
  {
    "name": "CFAI - CFAI Provence",
    "city": "Aix-en-Provence",
    "sector": "Centre de formation d'apprentis",
    "url": "https://diplomeo.com/etablissement-cfai_cfai_provence-568",
    "description": "",
    "address": "",
    "formations": [],
    "email": "Non trouvé",
    "email_found": false,
    "phone": "Non trouvé",
    "phone_found": false,
    "website": "Non trouvé",
    "website_found": false,
    "processed_at": "2025-03-19T05:30:41.489Z"
  },
  {
    "name": "CFAI 8002 - CFAI 8002 - site d'Amiens",
    "city": "Amiens",
    "sector": "Centre de formation d'apprentis",
    "url": "https://diplomeo.com/etablissement-cfai_8002_cfai_8002_site_d_amiens-569",
    "description": "",
    "address": "",
    "formations": [],
    "email": "Non trouvé",
    "email_found": false,
    "phone": "Non trouvé",
    "phone_found": false,
    "website": "Non trouvé",
    "website_found": false,
    "processed_at": "2025-03-19T05:30:47.228Z"
  },
  {
    "name": "CFAI OISE - PROMEO Formation - Compiègne",
    "city": "Compiègne",
    "sector": "Centre de formation d'apprentis",
    "url": "https://diplomeo.com/etablissement-cfai_oise_promeo_formation_compiegne-570",
    "description": "",
    "address": "",
    "formations": [],
    "email": "Non trouvé",
    "email_found": false,
    "phone": "Non trouvé",
    "phone_found": false,
    "website": "Non trouvé",
    "website_found": false,
    "processed_at": "2025-03-19T05:30:53.471Z"
  },
  {
    "name": "CFAI région Nord-Pas de Calais",
    "city": "Arras",
    "sector": "Centre de formation d'apprentis",
    "url": "https://diplomeo.com/etablissement-cfai_region_nord_pas_de_calais-571",
    "description": "",
    "address": "",
    "formations": [],
    "email": "Non trouvé",
    "email_found": false,
    "phone": "Non trouvé",
    "phone_found": false,
    "website": "Non trouvé",
    "website_found": false,
    "processed_at": "2025-03-19T05:30:59.734Z"
  },
  {
    "name": "CFAI - CFAI région Nord-Pas de Calais",
    "city": "Lille",
    "sector": "Centre de formation d'apprentis",
    "url": "https://diplomeo.com/etablissement-cfai_cfai_region_nord_pas_de_calais-572",
    "description": "",
    "address": "",
    "formations": [],
    "email": "Non trouvé",
    "email_found": false,
    "phone": "Non trouvé",
    "phone_found": false,
    "website": "Non trouvé",
    "website_found": false,
    "processed_at": "2025-03-19T05:31:05.755Z"
  },
  {
    "name": "CFAI OISE - PROMEO Formation - Beauvais",
    "city": "Compiègne",
    "sector": "Centre de formation d'apprentis",
    "url": "https://diplomeo.com/etablissement-cfai_oise_promeo_formation_beauvais-573",
    "description": "",
    "address": "",
    "formations": [],
    "email": "Non trouvé",
    "email_found": false,
    "phone": "Non trouvé",
    "phone_found": false,
    "website": "Non trouvé",
    "website_found": false,
    "processed_at": "2025-03-19T05:31:11.909Z"
  },
  {
    "name": "CFA interprofessionnel d'Indre et Loire",
    "city": "Tours",
    "sector": "Centre de formation d'apprentis",
    "url": "https://diplomeo.com/etablissement-cfa_interprofessionnel_d_indre_et_loire-574",
    "description": "",
    "address": "",
    "formations": [],
    "email": "Non trouvé",
    "email_found": false,
    "phone": "Non trouvé",
    "phone_found": false,
    "website": "Non trouvé",
    "website_found": false,
    "processed_at": "2025-03-19T05:31:18.052Z"
  },
  {
    "name": "CFA interprofessionnel Henri Martin",
    "city": "Carcassonne",
    "sector": "Centre de formation d'apprentis",
    "url": "https://diplomeo.com/etablissement-cfa_interprofessionnel_henri_martin-575",
    "description": "",
    "address": "",
    "formations": [],
    "email": "Non trouvé",
    "email_found": false,
    "phone": "Non trouvé",
    "phone_found": false,
    "website": "Non trouvé",
    "website_found": false,
    "processed_at": "2025-03-19T05:32:59.044Z"
  },
  {
    "name": "CFA interprofessionnel La Noue",
    "city": "Dijon",
    "sector": "Centre de formation d'apprentis",
    "url": "https://diplomeo.com/etablissement-cfa_interprofessionnel_la_noue-576",
    "description": "",
    "address": "",
    "formations": [],
    "email": "Non trouvé",
    "email_found": false,
    "phone": "Non trouvé",
    "phone_found": false,
    "website": "Non trouvé",
    "website_found": false,
    "processed_at": "2025-03-19T05:33:04.683Z"
  },
  {
    "name": "CFA interprofessionnel du Loir et Cher",
    "city": "Orléans",
    "sector": "Centre de formation d'apprentis",
    "url": "https://diplomeo.com/etablissement-cfa_interprofessionnel_du_loir_et_cher-577",
    "description": "",
    "address": "",
    "formations": [],
    "email": "Non trouvé",
    "email_found": false,
    "phone": "Non trouvé",
    "phone_found": false,
    "website": "Non trouvé",
    "website_found": false,
    "processed_at": "2025-03-19T05:33:10.790Z"
  },
  {
    "name": "CFAI OISE - PROMEO Formation - Senlis",
    "city": "Compiègne",
    "sector": "Centre de formation d'apprentis",
    "url": "https://diplomeo.com/etablissement-cfai_oise_promeo_formation_senlis-578",
    "description": "",
    "address": "",
    "formations": [],
    "email": "Non trouvé",
    "email_found": false,
    "phone": "Non trouvé",
    "phone_found": false,
    "website": "Non trouvé",
    "website_found": false,
    "processed_at": "2025-03-19T05:33:16.616Z"
  },
  {
    "name": "CFA du Cher - CFA interprofessionnel du Cher",
    "city": "Bourges",
    "sector": "Centre de formation d'apprentis",
    "url": "https://diplomeo.com/etablissement-cfa_du_cher_cfa_interprofessionnel_du_cher-579",
    "description": "",
    "address": "",
    "formations": [],
    "email": "Non trouvé",
    "email_found": false,
    "phone": "Non trouvé",
    "phone_found": false,
    "website": "Non trouvé",
    "website_found": false,
    "processed_at": "2025-03-19T05:33:22.869Z"
  },
  {
    "name": "CFA interprofessionnel de la Haute-Marne",
    "city": "Chaumont",
    "sector": "Centre de formation d'apprentis",
    "url": "https://diplomeo.com/etablissement-cfa_interprofessionnel_de_la_haute_marne-580",
    "description": "",
    "address": "",
    "formations": [],
    "email": "Non trouvé",
    "email_found": false,
    "phone": "Non trouvé",
    "phone_found": false,
    "website": "Non trouvé",
    "website_found": false,
    "processed_at": "2025-03-19T05:35:04.373Z"
  },
  {
    "name": "CFA interprofessionnel",
    "city": "Auxerre",
    "sector": "Centre de formation d'apprentis",
    "url": "https://diplomeo.com/etablissement-cfa_interprofessionnel-581",
    "description": "",
    "address": "",
    "formations": [],
    "email": "Non trouvé",
    "email_found": false,
    "phone": "Non trouvé",
    "phone_found": false,
    "website": "Non trouvé",
    "website_found": false,
    "processed_at": "2025-03-19T05:35:11.762Z"
  },
  {
    "name": "CFA interprofessionnel d'Eure et Loir",
    "city": "Chartres",
    "sector": "Centre de formation d'apprentis",
    "url": "https://diplomeo.com/etablissement-cfa_interprofessionnel_d_eure_et_loir-582",
    "description": "",
    "address": "",
    "formations": [],
    "email": "Non trouvé",
    "email_found": false,
    "phone": "Non trouvé",
    "phone_found": false,
    "website": "Non trouvé",
    "website_found": false,
    "processed_at": "2025-03-19T05:35:18.275Z"
  },
  {
    "name": "CFA interprofessionnel de Marne-La-Vallée (annexe)",
    "city": "Melun",
    "sector": "Centre de formation d'apprentis",
    "url": "https://diplomeo.com/etablissement-cfa_interprofessionnel_de_marne_la_vallee_annexe-583",
    "description": "",
    "address": "",
    "formations": [],
    "email": "Non trouvé",
    "email_found": false,
    "phone": "Non trouvé",
    "phone_found": false,
    "website": "Non trouvé",
    "website_found": false,
    "processed_at": "2025-03-19T05:36:58.120Z"
  },
  {
    "name": "CFA interprofessionnel de Marne-La-Vallée (annexe)",
    "city": "Melun",
    "sector": "Centre de formation d'apprentis",
    "url": "https://diplomeo.com/etablissement-cfa_interprofessionnel_de_marne_la_vallee_annexe-584",
    "description": "",
    "address": "",
    "formations": [],
    "email": "Non trouvé",
    "email_found": false,
    "phone": "Non trouvé",
    "phone_found": false,
    "website": "Non trouvé",
    "website_found": false,
    "processed_at": "2025-03-19T05:37:04.061Z"
  },
  {
    "name": "CFA de l'Industrie Seine-et-Marne",
    "city": "Melun",
    "sector": "Centre de formation d'apprentis",
    "url": "https://diplomeo.com/etablissement-cfa_de_l_industrie_seine_et_marne-585",
    "description": "",
    "address": "",
    "formations": [],
    "email": "Non trouvé",
    "email_found": false,
    "phone": "Non trouvé",
    "phone_found": false,
    "website": "Non trouvé",
    "website_found": false,
    "processed_at": "2025-03-19T05:38:45.479Z"
  },
  {
    "name": "CFA IMC - CFA institut des métiers et des compétences",
    "city": "Paris",
    "sector": "Centre de formation d'apprentis",
    "url": "https://diplomeo.com/etablissement-cfa_imc_cfa_institut_des_metiers_et_des_competences-588",
    "description": "",
    "address": "",
    "formations": [],
    "email": "Non trouvé",
    "email_found": false,
    "phone": "Non trouvé",
    "phone_found": false,
    "website": "Non trouvé",
    "website_found": false,
    "processed_at": "2025-03-19T05:38:52.390Z"
  },
  {
    "name": "CFA-IFA - CFA-Institut consulaire de formation d'Elbeuf",
    "city": "Rouen",
    "sector": "Centre de formation d'apprentis",
    "url": "https://diplomeo.com/etablissement-cfa_ifa_cfa_institut_consulaire_de_formation_d_elbeuf-589",
    "description": "",
    "address": "",
    "formations": [],
    "email": "Non trouvé",
    "email_found": false,
    "phone": "Non trouvé",
    "phone_found": false,
    "website": "Non trouvé",
    "website_found": false,
    "processed_at": "2025-03-19T05:38:58.852Z"
  },
  {
    "name": "CFA Industriel Marcel Sembat",
    "city": "Rouen",
    "sector": "Centre de formation d'apprentis",
    "url": "https://diplomeo.com/etablissement-cfa_industriel_marcel_sembat-590",
    "description": "",
    "address": "",
    "formations": [],
    "email": "Non trouvé",
    "email_found": false,
    "phone": "Non trouvé",
    "phone_found": false,
    "website": "Non trouvé",
    "website_found": false,
    "processed_at": "2025-03-19T05:39:05.200Z"
  },
  {
    "name": "CFA Industriel de la métallurgie",
    "city": "Rouen",
    "sector": "Centre de formation d'apprentis",
    "url": "https://diplomeo.com/etablissement-cfa_industriel_de_la_metallurgie-591",
    "description": "",
    "address": "",
    "formations": [],
    "email": "Non trouvé",
    "email_found": false,
    "phone": "Non trouvé",
    "phone_found": false,
    "website": "Non trouvé",
    "website_found": false,
    "processed_at": "2025-03-19T05:39:11.598Z"
  },
  {
    "name": "CFA IMT institut des métiers et techniques",
    "city": "Grenoble",
    "sector": "Centre de formation d'apprentis",
    "url": "https://diplomeo.com/etablissement-cfa_imt_institut_des_metiers_et_techniques-592",
    "description": "",
    "address": "",
    "formations": [],
    "email": "Non trouvé",
    "email_found": false,
    "phone": "Non trouvé",
    "phone_found": false,
    "website": "Non trouvé",
    "website_found": false,
    "processed_at": "2025-03-19T05:39:16.502Z"
  },
  {
    "name": "CCI Sud Formation CFA Languedoc-Roussillon - Perpignan",
    "city": "Perpignan",
    "sector": "Centre de formation d'apprentis",
    "url": "https://diplomeo.com/etablissement-cci_sud_formation_cfa_languedoc_roussillon_perpignan-593",
    "description": "",
    "address": "",
    "formations": [],
    "email": "Non trouvé",
    "email_found": false,
    "phone": "Non trouvé",
    "phone_found": false,
    "website": "Non trouvé",
    "website_found": false,
    "processed_at": "2025-03-19T05:39:23.214Z"
  },
  {
    "name": "CFA interprofessionnel de la Chambre de métiers et de l'artisanat du Var - Annexe Toulon La Valette",
    "city": "Toulon",
    "sector": "Centre de formation d'apprentis",
    "url": "https://diplomeo.com/etablissement-cfa_interprofessionnel_de_la_chambre_de_metiers_et_de_l_artisanat_du_var_annexe_toulon_la_valette-594",
    "description": "",
    "address": "",
    "formations": [],
    "email": "Non trouvé",
    "email_found": false,
    "phone": "Non trouvé",
    "phone_found": false,
    "website": "Non trouvé",
    "website_found": false,
    "processed_at": "2025-03-19T05:39:29.633Z"
  },
  {
    "name": "CFA interprofessionnel Alphonse Mounier (Corot)",
    "city": "Marseille",
    "sector": "Centre de formation d'apprentis",
    "url": "https://diplomeo.com/etablissement-cfa_interprofessionnel_alphonse_mounier_corot-595",
    "description": "",
    "address": "",
    "formations": [],
    "email": "Non trouvé",
    "email_found": false,
    "phone": "Non trouvé",
    "phone_found": false,
    "website": "Non trouvé",
    "website_found": false,
    "processed_at": "2025-03-19T05:39:35.916Z"
  },
  {
    "name": "CFAI - CFAI Moselle-CEFASIM",
    "city": "Metz",
    "sector": "Centre de formation d'apprentis",
    "url": "https://diplomeo.com/etablissement-cfai_cfai_moselle_cefasim-596",
    "description": "",
    "address": "",
    "formations": [],
    "email": "Non trouvé",
    "email_found": false,
    "phone": "Non trouvé",
    "phone_found": false,
    "website": "Non trouvé",
    "website_found": false,
    "processed_at": "2025-03-19T05:39:42.369Z"
  },
  {
    "name": "CFA interpro de la Marne",
    "city": "Reims",
    "sector": "Centre de formation d'apprentis",
    "url": "https://diplomeo.com/etablissement-cfa_interpro_de_la_marne-597",
    "description": "",
    "address": "",
    "formations": [],
    "email": "Non trouvé",
    "email_found": false,
    "phone": "Non trouvé",
    "phone_found": false,
    "website": "Non trouvé",
    "website_found": false,
    "processed_at": "2025-03-19T05:39:47.867Z"
  },
  {
    "name": "INTERFOR - Amiens",
    "city": "Amiens",
    "sector": "Centre de formation d'apprentis",
    "url": "https://diplomeo.com/etablissement-interfor_amiens-598",
    "description": "",
    "address": "",
    "formations": [],
    "email": "Non trouvé",
    "email_found": false,
    "phone": "Non trouvé",
    "phone_found": false,
    "website": "Non trouvé",
    "website_found": false,
    "processed_at": "2025-03-19T05:39:53.971Z"
  },
  {
    "name": "CFAI MP - CFAI Midi-Pyrénées",
    "city": "Toulouse",
    "sector": "Centre de formation d'apprentis",
    "url": "https://diplomeo.com/etablissement-cfai_mp_cfai_midi_pyrenees-599",
    "description": "",
    "address": "",
    "formations": [],
    "email": "Non trouvé",
    "email_found": false,
    "phone": "Non trouvé",
    "phone_found": false,
    "website": "Non trouvé",
    "website_found": false,
    "processed_at": "2025-03-19T05:39:59.880Z"
  },
  {
    "name": "CFA IFA - CFA-IFA Montivilliers",
    "city": "Rouen",
    "sector": "Centre de formation d'apprentis",
    "url": "https://diplomeo.com/etablissement-cfa_ifa_cfa_ifa_montivilliers-600",
    "description": "",
    "address": "",
    "formations": [],
    "email": "Non trouvé",
    "email_found": false,
    "phone": "Non trouvé",
    "phone_found": false,
    "website": "Non trouvé",
    "website_found": false,
    "processed_at": "2025-03-19T05:41:40.704Z"
  },
  {
    "name": "CFAI Loire de l'AFIL - Saint-Etienne",
    "city": "Saint-Étienne",
    "sector": "Centre de formation d'apprentis",
    "url": "https://diplomeo.com/etablissement-cfai_loire_de_l_afil_saint_etienne-601",
    "description": "",
    "address": "",
    "formations": [],
    "email": "Non trouvé",
    "email_found": false,
    "phone": "Non trouvé",
    "phone_found": false,
    "website": "Non trouvé",
    "website_found": false,
    "processed_at": "2025-03-19T05:41:46.513Z"
  }
]