[
  {
    "name": "L’École Hermès des savoir-faire - Guyenne - Saint-Vincent-de-Paul",
    "city": "Saint-Vincent-de-Paul",
    "sector": "Centre de formation d'apprentis",
    "url": "https://diplomeo.com/etablissement-l_ecole_hermes_des_savoir_faire_guyenne_saint_vincent_de_paul-22987",
    "description": "",
    "address": "",
    "formations": [],
    "email": "Non trouvé",
    "email_found": false,
    "phone": "Non trouvé",
    "phone_found": false,
    "website": "https://ecole.hermes.com/lecole/?utm_source=Diplomeo&utm_medium=backlink&utm_campaign=pages_ecoles&utm_content=bouton?utm_source=diplomeos",
    "website_found": true,
    "processed_at": "2025-03-19T02:56:29.604Z"
  },
  {
    "name": "Ecole IT - Campus d'Amiens",
    "city": "Amiens",
    "sector": "École de l'internet",
    "url": "https://diplomeo.com/etablissement-ecole_it_campus_d_amiens-22998",
    "description": "",
    "address": "",
    "formations": [],
    "email": "justine.lephay@ecole-it.coms",
    "email_found": true,
    "phone": "33681020403",
    "phone_found": true,
    "website": "https://ecole-it.com?utm_source=diplomeos",
    "website_found": true,
    "processed_at": "2025-03-19T02:56:41.213Z"
  },
  {
    "name": "L’École Hermès des savoir-faire - Val de Vence",
    "city": "Charleville-Mézières",
    "sector": "Centre de formation d'apprentis",
    "url": "https://diplomeo.com/etablissement-l_ecole_hermes_des_savoir_faire_val_de_vence-23073",
    "description": "",
    "address": "",
    "formations": [],
    "email": "Non trouvé",
    "email_found": false,
    "phone": "Non trouvé",
    "phone_found": false,
    "website": "https://ecole.hermes.com/lecole/?utm_source=Diplomeo&utm_medium=backlink&utm_campaign=pages_ecoles&utm_content=bouton?utm_source=diplomeos",
    "website_found": true,
    "processed_at": "2025-03-19T02:56:48.261Z"
  },
  {
    "name": "L’École Hermès des savoir-faire - Riom",
    "city": "Riom",
    "sector": "Centre de formation d'apprentis",
    "url": "https://diplomeo.com/etablissement-l_ecole_hermes_des_savoir_faire_riom-23074",
    "description": "",
    "address": "",
    "formations": [],
    "email": "Non trouvé",
    "email_found": false,
    "phone": "Non trouvé",
    "phone_found": false,
    "website": "https://ecole.hermes.com/lecole/?utm_source=Diplomeo&utm_medium=backlink&utm_campaign=pages_ecoles&utm_content=bouton?utm_source=diplomeos",
    "website_found": true,
    "processed_at": "2025-03-19T02:56:55.737Z"
  },
  {
    "name": "Faculté Des Métiers - Lorient",
    "city": "Lorient",
    "sector": "Centre de formation d'apprentis",
    "url": "https://diplomeo.com/etablissement-faculte_des_metiers_lorient-23080",
    "description": "",
    "address": "",
    "formations": [],
    "email": "formation.alternance@morbihan.cci.frs",
    "email_found": true,
    "phone": "33297640454",
    "phone_found": true,
    "website": "https://www.fac-metiers.fr/etablissement/faculte-des-metiers-lorient?utm_source=diplomeos",
    "website_found": true,
    "processed_at": "2025-03-19T02:57:07.923Z"
  },
  {
    "name": "IHECF Montpellier",
    "city": "Montpellier",
    "sector": "École de gestion et de commerce",
    "url": "https://diplomeo.com/etablissement-ihecf_montpellier-23171",
    "description": "",
    "address": "",
    "formations": [],
    "email": "montpellier@ihecf.frs",
    "email_found": true,
    "phone": "33467105857",
    "phone_found": true,
    "website": "https://www.ihecf.fr/?utm_source=diplomeos",
    "website_found": true,
    "processed_at": "2025-03-19T02:57:16.591Z"
  },
  {
    "name": "Ecole de design Nantes Atlantique",
    "city": "Nantes",
    "sector": "École d'art",
    "url": "https://diplomeo.com/etablissement-ecole_de_design_nantes_atlantique-84",
    "description": "",
    "address": "",
    "formations": [],
    "email": "Non trouvé",
    "email_found": false,
    "phone": "Non trouvé",
    "phone_found": false,
    "website": "Non trouvé",
    "website_found": false,
    "processed_at": "2025-03-19T02:57:22.431Z"
  },
  {
    "name": "IGS-RH  Lyon",
    "city": "Lyon",
    "sector": "École de ressources humaines",
    "url": "https://diplomeo.com/etablissement-igs_rh_lyon-1254",
    "description": "",
    "address": "",
    "formations": [],
    "email": "Non trouvé",
    "email_found": false,
    "phone": "Non trouvé",
    "phone_found": false,
    "website": "Non trouvé",
    "website_found": false,
    "processed_at": "2025-03-19T02:57:28.991Z"
  },
  {
    "name": "ISO - Institut Supérieur d'Optique Rennes",
    "city": "Rennes",
    "sector": "École de santé",
    "url": "https://diplomeo.com/etablissement-iso_institut_superieur_d_optique_rennes-1770",
    "description": "",
    "address": "",
    "formations": [],
    "email": "Non trouvé",
    "email_found": false,
    "phone": "Non trouvé",
    "phone_found": false,
    "website": "Non trouvé",
    "website_found": false,
    "processed_at": "2025-03-19T02:57:35.369Z"
  },
  {
    "name": "Ecole La Pradette",
    "city": "Toulouse",
    "sector": "École du secteur social",
    "url": "https://diplomeo.com/etablissement-ecole_la_pradette-1773",
    "description": "",
    "address": "",
    "formations": [],
    "email": "Non trouvé",
    "email_found": false,
    "phone": "Non trouvé",
    "phone_found": false,
    "website": "Non trouvé",
    "website_found": false,
    "processed_at": "2025-03-19T02:57:41.686Z"
  },
  {
    "name": "Ecole Supérieure de Design de Troyes",
    "city": "Troyes",
    "sector": "Design, Graphisme, 3D, Vidéo, Mode",
    "url": "https://diplomeo.com/etablissement-ecole_superieure_de_design_de_troyes-1942",
    "description": "",
    "address": "",
    "formations": [],
    "email": "Non trouvé",
    "email_found": false,
    "phone": "Non trouvé",
    "phone_found": false,
    "website": "Non trouvé",
    "website_found": false,
    "processed_at": "2025-03-19T02:57:47.737Z"
  },
  {
    "name": "Ecole supérieure de commerce, de communication et de gestion - Nice",
    "city": "Nice",
    "sector": "École de gestion et de commerce",
    "url": "https://diplomeo.com/etablissement-ecole_superieure_de_commerce_de_communication_et_de_gestion_nice-1963",
    "description": "",
    "address": "",
    "formations": [],
    "email": "Non trouvé",
    "email_found": false,
    "phone": "Non trouvé",
    "phone_found": false,
    "website": "Non trouvé",
    "website_found": false,
    "processed_at": "2025-03-19T02:57:52.492Z"
  },
  {
    "name": "Ecole supérieure de commerce, de communication et de gestion - Cannes",
    "city": "Cannes",
    "sector": "École de gestion et de commerce",
    "url": "https://diplomeo.com/etablissement-ecole_superieure_de_commerce_de_communication_et_de_gestion_cannes-1965",
    "description": "",
    "address": "",
    "formations": [],
    "email": "Non trouvé",
    "email_found": false,
    "phone": "Non trouvé",
    "phone_found": false,
    "website": "Non trouvé",
    "website_found": false,
    "processed_at": "2025-03-19T02:59:34.296Z"
  },
  {
    "name": "École Internationale Tunon - Caen",
    "city": "Caen",
    "sector": "Autre établissement d'enseignement",
    "url": "https://diplomeo.com/etablissement-ecole_internationale_tunon_caen-2279",
    "description": "",
    "address": "",
    "formations": [],
    "email": "Non trouvé",
    "email_found": false,
    "phone": "Non trouvé",
    "phone_found": false,
    "website": "Non trouvé",
    "website_found": false,
    "processed_at": "2025-03-19T02:59:39.939Z"
  },
  {
    "name": "EFC - Ecole française de comptabilité",
    "city": "Lyon",
    "sector": "Campus connecté",
    "url": "https://diplomeo.com/etablissement-efc_ecole_francaise_de_comptabilite-2325",
    "description": "",
    "address": "",
    "formations": [],
    "email": "Non trouvé",
    "email_found": false,
    "phone": "Non trouvé",
    "phone_found": false,
    "website": "Non trouvé",
    "website_found": false,
    "processed_at": "2025-03-19T02:59:45.800Z"
  },
  {
    "name": "SCBS - South Champagne Business School - Troyes",
    "city": "Troyes",
    "sector": "École de gestion et de commerce",
    "url": "https://diplomeo.com/etablissement-scbs_south_champagne_business_school_troyes-2918",
    "description": "",
    "address": "",
    "formations": [],
    "email": "Non trouvé",
    "email_found": false,
    "phone": "Non trouvé",
    "phone_found": false,
    "website": "Non trouvé",
    "website_found": false,
    "processed_at": "2025-03-19T02:59:52.366Z"
  },
  {
    "name": "ISO - Institut Supérieur d'Optique Nancy",
    "city": "Nancy",
    "sector": "École de santé",
    "url": "https://diplomeo.com/etablissement-iso_institut_superieur_d_optique_nancy-4196",
    "description": "",
    "address": "",
    "formations": [],
    "email": "Non trouvé",
    "email_found": false,
    "phone": "Non trouvé",
    "phone_found": false,
    "website": "Non trouvé",
    "website_found": false,
    "processed_at": "2025-03-19T03:01:33.976Z"
  },
  {
    "name": "Ecole Pigier - Clermont Ferrand",
    "city": "Clermont-Ferrand",
    "sector": "École de gestion et de commerce",
    "url": "https://diplomeo.com/etablissement-ecole_pigier_clermont_ferrand-5044",
    "description": "",
    "address": "",
    "formations": [],
    "email": "Non trouvé",
    "email_found": false,
    "phone": "Non trouvé",
    "phone_found": false,
    "website": "Non trouvé",
    "website_found": false,
    "processed_at": "2025-03-19T03:01:40.638Z"
  },
  {
    "name": "Ynov informatique - Bordeaux",
    "city": "Bordeaux",
    "sector": "École d'ingénierie informatique",
    "url": "https://diplomeo.com/etablissement-ynov_informatique_bordeaux-7301",
    "description": "",
    "address": "",
    "formations": [],
    "email": "Non trouvé",
    "email_found": false,
    "phone": "Non trouvé",
    "phone_found": false,
    "website": "Non trouvé",
    "website_found": false,
    "processed_at": "2025-03-19T03:01:46.874Z"
  },
  {
    "name": "Ynov informatique - Aix en Provence",
    "city": "Aix-en-Provence",
    "sector": "École d'ingénierie informatique",
    "url": "https://diplomeo.com/etablissement-ynov_informatique_aix_en_provence-7302",
    "description": "",
    "address": "",
    "formations": [],
    "email": "Non trouvé",
    "email_found": false,
    "phone": "Non trouvé",
    "phone_found": false,
    "website": "Non trouvé",
    "website_found": false,
    "processed_at": "2025-03-19T03:01:52.961Z"
  },
  {
    "name": "Ynov informatique - Toulouse",
    "city": "Toulouse",
    "sector": "École d'ingénierie informatique",
    "url": "https://diplomeo.com/etablissement-ynov_informatique_toulouse-7303",
    "description": "",
    "address": "",
    "formations": [],
    "email": "Non trouvé",
    "email_found": false,
    "phone": "Non trouvé",
    "phone_found": false,
    "website": "Non trouvé",
    "website_found": false,
    "processed_at": "2025-03-19T03:01:57.763Z"
  },
  {
    "name": "Stan Santé FormaSup - Nancy",
    "city": "Nancy",
    "sector": "Classes préparatoires aux concours",
    "url": "https://diplomeo.com/etablissement-stan_sante_formasup_nancy-7438",
    "description": "",
    "address": "",
    "formations": [],
    "email": "Non trouvé",
    "email_found": false,
    "phone": "Non trouvé",
    "phone_found": false,
    "website": "Non trouvé",
    "website_found": false,
    "processed_at": "2025-03-19T03:02:03.740Z"
  },
  {
    "name": "SupDijon",
    "city": "Dijon",
    "sector": "Classes préparatoires aux concours",
    "url": "https://diplomeo.com/etablissement-supdijon-7439",
    "description": "",
    "address": "",
    "formations": [],
    "email": "Non trouvé",
    "email_found": false,
    "phone": "Non trouvé",
    "phone_found": false,
    "website": "Non trouvé",
    "website_found": false,
    "processed_at": "2025-03-19T03:03:45.052Z"
  },
  {
    "name": "Supexam - Nantes",
    "city": "Nantes",
    "sector": "Classes préparatoires aux concours",
    "url": "https://diplomeo.com/etablissement-supexam_nantes-7442",
    "description": "",
    "address": "",
    "formations": [],
    "email": "Non trouvé",
    "email_found": false,
    "phone": "Non trouvé",
    "phone_found": false,
    "website": "Non trouvé",
    "website_found": false,
    "processed_at": "2025-03-19T03:03:51.913Z"
  },
  {
    "name": "Prépa Epsilon",
    "city": "Paris",
    "sector": "Classes préparatoires aux concours",
    "url": "https://diplomeo.com/etablissement-prepa_epsilon-7547",
    "description": "",
    "address": "",
    "formations": [],
    "email": "Non trouvé",
    "email_found": false,
    "phone": "Non trouvé",
    "phone_found": false,
    "website": "Non trouvé",
    "website_found": false,
    "processed_at": "2025-03-19T03:03:58.347Z"
  },
  {
    "name": "Bersot Formation",
    "city": "Besançon",
    "sector": "Classes préparatoires aux concours",
    "url": "https://diplomeo.com/etablissement-bersot_formation-7548",
    "description": "",
    "address": "",
    "formations": [],
    "email": "Non trouvé",
    "email_found": false,
    "phone": "Non trouvé",
    "phone_found": false,
    "website": "Non trouvé",
    "website_found": false,
    "processed_at": "2025-03-19T03:04:03.813Z"
  },
  {
    "name": "Ecole Chez Soi",
    "city": "Paris",
    "sector": "Campus connecté",
    "url": "https://diplomeo.com/etablissement-ecole_chez_soi-7603",
    "description": "",
    "address": "",
    "formations": [],
    "email": "Non trouvé",
    "email_found": false,
    "phone": "Non trouvé",
    "phone_found": false,
    "website": "Non trouvé",
    "website_found": false,
    "processed_at": "2025-03-19T03:04:10.200Z"
  },
  {
    "name": "Studi Finance & RH",
    "city": "Montpellier",
    "sector": "Campus connecté",
    "url": "https://diplomeo.com/etablissement-studi_finance_rh-7627",
    "description": "",
    "address": "",
    "formations": [],
    "email": "Non trouvé",
    "email_found": false,
    "phone": "Non trouvé",
    "phone_found": false,
    "website": "Non trouvé",
    "website_found": false,
    "processed_at": "2025-03-19T03:04:15.559Z"
  },
  {
    "name": "Lignes & Formations",
    "city": "Paris",
    "sector": "Campus connecté",
    "url": "https://diplomeo.com/etablissement-lignes_formations-7763",
    "description": "",
    "address": "",
    "formations": [],
    "email": "Non trouvé",
    "email_found": false,
    "phone": "Non trouvé",
    "phone_found": false,
    "website": "Non trouvé",
    "website_found": false,
    "processed_at": "2025-03-19T03:04:22.067Z"
  },
  {
    "name": "Ynov informatique - Lyon",
    "city": "Lyon",
    "sector": "École d'ingénierie informatique",
    "url": "https://diplomeo.com/etablissement-ynov_informatique_lyon-7855",
    "description": "",
    "address": "",
    "formations": [],
    "email": "Non trouvé",
    "email_found": false,
    "phone": "Non trouvé",
    "phone_found": false,
    "website": "Non trouvé",
    "website_found": false,
    "processed_at": "2025-03-19T03:04:28.654Z"
  },
  {
    "name": "Centre Européen de Formation",
    "city": "Villeneuve-d'Ascq",
    "sector": "Campus connecté",
    "url": "https://diplomeo.com/etablissement-centre_europeen_de_formation-7874",
    "description": "",
    "address": "",
    "formations": [],
    "email": "Non trouvé",
    "email_found": false,
    "phone": "Non trouvé",
    "phone_found": false,
    "website": "Non trouvé",
    "website_found": false,
    "processed_at": "2025-03-19T03:06:09.663Z"
  },
  {
    "name": "EDAA Ecole d'art à distance",
    "city": "Reims",
    "sector": "Campus connecté",
    "url": "https://diplomeo.com/etablissement-edaa_ecole_d_art_a_distance-7929",
    "description": "",
    "address": "",
    "formations": [],
    "email": "Non trouvé",
    "email_found": false,
    "phone": "Non trouvé",
    "phone_found": false,
    "website": "Non trouvé",
    "website_found": false,
    "processed_at": "2025-03-19T03:06:16.610Z"
  },
  {
    "name": "Ynov informatique -  Nantes",
    "city": "Nantes",
    "sector": "École d'ingénierie informatique",
    "url": "https://diplomeo.com/etablissement-ynov_informatique_nantes-8117",
    "description": "",
    "address": "",
    "formations": [],
    "email": "Non trouvé",
    "email_found": false,
    "phone": "Non trouvé",
    "phone_found": false,
    "website": "Non trouvé",
    "website_found": false,
    "processed_at": "2025-03-19T03:06:23.019Z"
  },
  {
    "name": "EGE Ecole de Guerre Economique - ESLSCA Business School",
    "city": "Paris",
    "sector": "École de gestion et de commerce",
    "url": "https://diplomeo.com/etablissement-ege_ecole_de_guerre_economique_eslsca_business_school-8508",
    "description": "",
    "address": "",
    "formations": [],
    "email": "Non trouvé",
    "email_found": false,
    "phone": "Non trouvé",
    "phone_found": false,
    "website": "Non trouvé",
    "website_found": false,
    "processed_at": "2025-03-19T03:06:29.573Z"
  },
  {
    "name": "Institut Rousseau",
    "city": "Toulouse",
    "sector": "Autre établissement d'enseignement",
    "url": "https://diplomeo.com/etablissement-institut_rousseau-9363",
    "description": "",
    "address": "",
    "formations": [],
    "email": "Non trouvé",
    "email_found": false,
    "phone": "Non trouvé",
    "phone_found": false,
    "website": "Non trouvé",
    "website_found": false,
    "processed_at": "2025-03-19T03:06:36.007Z"
  },
  {
    "name": "Studi Business School",
    "city": "Montpellier",
    "sector": "Campus connecté",
    "url": "https://diplomeo.com/etablissement-studi_business_school-9374",
    "description": "",
    "address": "",
    "formations": [],
    "email": "Non trouvé",
    "email_found": false,
    "phone": "Non trouvé",
    "phone_found": false,
    "website": "Non trouvé",
    "website_found": false,
    "processed_at": "2025-03-19T03:08:16.310Z"
  },
  {
    "name": "ESDAC Clermont Ferrand",
    "city": "Clermont-Ferrand",
    "sector": "Design, Graphisme, 3D, Vidéo, Mode",
    "url": "https://diplomeo.com/etablissement-esdac_clermont_ferrand-9770",
    "description": "",
    "address": "",
    "formations": [],
    "email": "Non trouvé",
    "email_found": false,
    "phone": "Non trouvé",
    "phone_found": false,
    "website": "Non trouvé",
    "website_found": false,
    "processed_at": "2025-03-19T03:08:21.840Z"
  },
  {
    "name": "IPI - Ecole d'informatique - Toulouse",
    "city": "Blagnac",
    "sector": "École de l'internet",
    "url": "https://diplomeo.com/etablissement-ipi_ecole_d_informatique_toulouse-10000",
    "description": "",
    "address": "",
    "formations": [],
    "email": "Non trouvé",
    "email_found": false,
    "phone": "Non trouvé",
    "phone_found": false,
    "website": "Non trouvé",
    "website_found": false,
    "processed_at": "2025-03-19T03:08:27.848Z"
  },
  {
    "name": "Ynov Création & Digital Design - Bordeaux",
    "city": "Bordeaux",
    "sector": "Design, Graphisme, 3D, Vidéo, Mode",
    "url": "https://diplomeo.com/etablissement-ynov_creation_digital_design_bordeaux-10093",
    "description": "",
    "address": "",
    "formations": [],
    "email": "Non trouvé",
    "email_found": false,
    "phone": "Non trouvé",
    "phone_found": false,
    "website": "Non trouvé",
    "website_found": false,
    "processed_at": "2025-03-19T03:08:33.585Z"
  },
  {
    "name": "Ynov 3D, Animation & Jeux Vidéo - Bordeaux",
    "city": "Bordeaux",
    "sector": "Design, Graphisme, 3D, Vidéo, Mode",
    "url": "https://diplomeo.com/etablissement-ynov_3d_animation_jeux_video_bordeaux-10094",
    "description": "",
    "address": "",
    "formations": [],
    "email": "Non trouvé",
    "email_found": false,
    "phone": "Non trouvé",
    "phone_found": false,
    "website": "Non trouvé",
    "website_found": false,
    "processed_at": "2025-03-19T03:08:40.249Z"
  },
  {
    "name": "Ynov Audiovisuel - Bordeaux",
    "city": "Bordeaux",
    "sector": "École de l'internet",
    "url": "https://diplomeo.com/etablissement-ynov_audiovisuel_bordeaux-10095",
    "description": "",
    "address": "",
    "formations": [],
    "email": "Non trouvé",
    "email_found": false,
    "phone": "Non trouvé",
    "phone_found": false,
    "website": "Non trouvé",
    "website_found": false,
    "processed_at": "2025-03-19T03:08:46.211Z"
  },
  {
    "name": "Ynov Création & Digital Design - Lyon",
    "city": "Lyon",
    "sector": "Design, Graphisme, 3D, Vidéo, Mode",
    "url": "https://diplomeo.com/etablissement-ynov_creation_digital_design_lyon-10096",
    "description": "",
    "address": "",
    "formations": [],
    "email": "Non trouvé",
    "email_found": false,
    "phone": "Non trouvé",
    "phone_found": false,
    "website": "Non trouvé",
    "website_found": false,
    "processed_at": "2025-03-19T03:08:51.761Z"
  },
  {
    "name": "Ynov Audiovisuel - Lyon",
    "city": "Lyon",
    "sector": "École de l'internet",
    "url": "https://diplomeo.com/etablissement-ynov_audiovisuel_lyon-10097",
    "description": "",
    "address": "",
    "formations": [],
    "email": "Non trouvé",
    "email_found": false,
    "phone": "Non trouvé",
    "phone_found": false,
    "website": "Non trouvé",
    "website_found": false,
    "processed_at": "2025-03-19T03:08:57.746Z"
  },
  {
    "name": "Ynov 3D, Animation & Jeux Vidéo - Lyon",
    "city": "Lyon",
    "sector": "Design, Graphisme, 3D, Vidéo, Mode",
    "url": "https://diplomeo.com/etablissement-ynov_3d_animation_jeux_video_lyon-10098",
    "description": "",
    "address": "",
    "formations": [],
    "email": "Non trouvé",
    "email_found": false,
    "phone": "Non trouvé",
    "phone_found": false,
    "website": "Non trouvé",
    "website_found": false,
    "processed_at": "2025-03-19T03:09:03.683Z"
  },
  {
    "name": "Ynov Marketing & Communication - Nantes",
    "city": "Nantes",
    "sector": "École spécialisée",
    "url": "https://diplomeo.com/etablissement-ynov_marketing_communication_nantes-10100",
    "description": "",
    "address": "",
    "formations": [],
    "email": "Non trouvé",
    "email_found": false,
    "phone": "Non trouvé",
    "phone_found": false,
    "website": "Non trouvé",
    "website_found": false,
    "processed_at": "2025-03-19T03:09:09.606Z"
  },
  {
    "name": "Ynov 3D, Animation & Jeux Vidéo - Nantes",
    "city": "Nantes",
    "sector": "Design, Graphisme, 3D, Vidéo, Mode",
    "url": "https://diplomeo.com/etablissement-ynov_3d_animation_jeux_video_nantes-10101",
    "description": "",
    "address": "",
    "formations": [],
    "email": "Non trouvé",
    "email_found": false,
    "phone": "Non trouvé",
    "phone_found": false,
    "website": "Non trouvé",
    "website_found": false,
    "processed_at": "2025-03-19T03:09:15.712Z"
  },
  {
    "name": "Ynov Audiovisuel - Nantes",
    "city": "Nantes",
    "sector": "École de l'internet",
    "url": "https://diplomeo.com/etablissement-ynov_audiovisuel_nantes-10102",
    "description": "",
    "address": "",
    "formations": [],
    "email": "Non trouvé",
    "email_found": false,
    "phone": "Non trouvé",
    "phone_found": false,
    "website": "Non trouvé",
    "website_found": false,
    "processed_at": "2025-03-19T03:09:22.013Z"
  },
  {
    "name": "Ynov Création & Digital Design - Nantes",
    "city": "Nantes",
    "sector": "Design, Graphisme, 3D, Vidéo, Mode",
    "url": "https://diplomeo.com/etablissement-ynov_creation_digital_design_nantes-10103",
    "description": "",
    "address": "",
    "formations": [],
    "email": "Non trouvé",
    "email_found": false,
    "phone": "Non trouvé",
    "phone_found": false,
    "website": "Non trouvé",
    "website_found": false,
    "processed_at": "2025-03-19T03:09:28.466Z"
  },
  {
    "name": "Ynov Marketing & Communication - Aix en Provence",
    "city": "Aix-en-Provence",
    "sector": "École spécialisée",
    "url": "https://diplomeo.com/etablissement-ynov_marketing_communication_aix_en_provence-10104",
    "description": "",
    "address": "",
    "formations": [],
    "email": "Non trouvé",
    "email_found": false,
    "phone": "Non trouvé",
    "phone_found": false,
    "website": "Non trouvé",
    "website_found": false,
    "processed_at": "2025-03-19T03:09:34.762Z"
  },
  {
    "name": "Ynov 3D, Animation & Jeux Vidéo - Aix en Provence",
    "city": "Aix-en-Provence",
    "sector": "Design, Graphisme, 3D, Vidéo, Mode",
    "url": "https://diplomeo.com/etablissement-ynov_3d_animation_jeux_video_aix_en_provence-10105",
    "description": "",
    "address": "",
    "formations": [],
    "email": "Non trouvé",
    "email_found": false,
    "phone": "Non trouvé",
    "phone_found": false,
    "website": "Non trouvé",
    "website_found": false,
    "processed_at": "2025-03-19T03:09:40.841Z"
  }
]